COPYING
MANIFEST.in
README
setup.cfg
setup.py
doc/API.rst
doc/Client.rst
doc/Documentation.rst
doc/Examples.rst
doc/Installation.rst
doc/Intro.rst
doc/Makefile
doc/Modeldef.rst
doc/Personis.pdf
doc/README
doc/Server.rst
doc/Tests.rst
doc/Tutorial.rst
doc/accretion.jpg
doc/conf.py
doc/index.rst
doc/model-tree.jpg
doc/personis.client.rst
doc/personis.rst
doc/personis.server.rst
doc/resolution.jpg
personis/__init__.py
personis.egg-info/PKG-INFO
personis.egg-info/SOURCES.txt
personis.egg-info/dependency_links.txt
personis.egg-info/entry_points.txt
personis.egg-info/requires.txt
personis.egg-info/top_level.txt
personis/app_client/__init__.py
personis/client/__init__.py
personis/client/util.py
personis/examples/__init__.py
personis/examples/activity/__init__.py
personis/examples/activity/__main__.py
personis/examples/activity/client_secrets.json
personis/examples/aelog/__init__.py
personis/examples/aelog/app.html
personis/examples/aelog/app.yaml
personis/examples/aelog/appengine_config.py
personis/examples/aelog/deploy.sh
personis/examples/aelog/gflags.py
personis/examples/aelog/gflags_validators.py
personis/examples/aelog/log-llum.py
personis/examples/aelog/oauth.ae.yaml
personis/examples/aelog/oauth.ent.yaml
personis/examples/aelog/oauth.yaml
personis/examples/aelog/apiclient/__init__.py
personis/examples/aelog/apiclient/discovery.py
personis/examples/aelog/apiclient/errors.py
personis/examples/aelog/apiclient/http.py
personis/examples/aelog/apiclient/mimeparse.py
personis/examples/aelog/apiclient/model.py
personis/examples/aelog/apiclient/schema.py
personis/examples/aelog/gaesessions/__init__.py
personis/examples/aelog/httplib2/__init__.py
personis/examples/aelog/httplib2/cacerts.txt
personis/examples/aelog/httplib2/iri2uri.py
personis/examples/aelog/httplib2/socks.py
personis/examples/aelog/oauth2client/__init__.py
personis/examples/aelog/oauth2client/anyjson.py
personis/examples/aelog/oauth2client/appengine.py
personis/examples/aelog/oauth2client/client.py
personis/examples/aelog/oauth2client/clientsecrets.py
personis/examples/aelog/oauth2client/crypt.py
personis/examples/aelog/oauth2client/django_orm.py
personis/examples/aelog/oauth2client/file.py
