Metadata-Version: 1.1
Name: personis
Version: 0.933
Summary: Peronis user model library
Home-page: http://github.com/jbu/personis
Author: Bob Kummerfeld, James Uther, Mark Assad, Judy Kay, et. al.
Author-email: bob.kummerfeld@sydney.edu.au
License: GPL3
Keywords: personis user-model server
Platform: UNKNOWN
Classifier: Development Status :: 4 - Beta
Classifier: Intended Audience :: Science/Research
Classifier: License :: OSI Approved :: GNU General Public License v3 or later (GPLv3+)
Classifier: Operating System :: POSIX
Classifier: Framework :: CherryPy
Classifier: Programming Language :: Python
Classifier: Topic :: Scientific/Engineering :: Human Machine Interfaces
